.coveragerc
.stestr.conf
.travis.yml
AUTHORS
CHANGELOG.md
ChangeLog
LICENSE
MANIFEST.in
README.md
requirements.txt
setup.cfg
setup.py
test-requirements.txt
tox.ini
config/networking-oneview-config-generator.conf
etc/neutron/plugins/ml2/ml2_conf_oneview.ini.sample
networking_oneview/__init__.py
networking_oneview.egg-info/PKG-INFO
networking_oneview.egg-info/SOURCES.txt
networking_oneview.egg-info/dependency_links.txt
networking_oneview.egg-info/entry_points.txt
networking_oneview.egg-info/not-zip-safe
networking_oneview.egg-info/pbr.json
networking_oneview.egg-info/requires.txt
networking_oneview.egg-info/top_level.txt
networking_oneview/common/.gitkeep
networking_oneview/common/__init__.py
networking_oneview/conf/__init__.py
networking_oneview/conf/default.py
networking_oneview/conf/oneview.py
networking_oneview/conf/opts.py
networking_oneview/db/__init__.py
networking_oneview/db/oneview_network_db.py
networking_oneview/db/migration/__init__.py
networking_oneview/db/migration/alembic_migrations/__init__.py
networking_oneview/db/migration/alembic_migrations/env.py
networking_oneview/db/migration/alembic_migrations/script.py.mako
networking_oneview/db/migration/alembic_migrations/versions/56529a79cf3b_initial_db_version.py
networking_oneview/db/migration/alembic_migrations/versions/__init__.py
networking_oneview/ml2/__init__.py
networking_oneview/ml2/drivers/__init__.py
networking_oneview/ml2/drivers/oneview/__init__.py
networking_oneview/ml2/drivers/oneview/common.py
networking_oneview/ml2/drivers/oneview/database_manager.py
networking_oneview/ml2/drivers/oneview/exceptions.py
networking_oneview/ml2/drivers/oneview/mech_oneview.py
networking_oneview/ml2/drivers/oneview/neutron_oneview_client.py
networking_oneview/ml2/drivers/oneview/synchronization.py
networking_oneview/samples/ml2_conf.ini
networking_oneview/tests/__init__.py
networking_oneview/tests/unit/__init__.py
networking_oneview/tests/unit/ml2/__init__.py
networking_oneview/tests/unit/ml2/drivers/__init__.py
networking_oneview/tests/unit/ml2/drivers/oneview/__init__.py
networking_oneview/tests/unit/ml2/drivers/oneview/test_common.py
networking_oneview/tests/unit/ml2/drivers/oneview/test_networking_oneview.py
networking_oneview/tests/unit/ml2/drivers/oneview/test_oneview_mech_driver.py
