Metadata-Version: 1.1
Name: networking-oneview
Version: 1.1.0
Summary: HPE OneView Mechanism Driver for Neutron ML2 plugin
Home-page: https://github.com/HewlettPackard/networking-oneview
Author: UFCG
Author-email: ricardo@lsd.ufcg.edu.br
License: UNKNOWN
Platform: UNKNOWN
Classifier: Environment :: OpenStack
Classifier: Intended Audience :: Information Technology
Classifier: Intended Audience :: System Administrators
Classifier: License :: OSI Approved :: Apache Software License
Classifier: Operating System :: POSIX :: Linux
Classifier: Programming Language :: Python
Classifier: Programming Language :: Python :: 2
Classifier: Programming Language :: Python :: 2.7
Classifier: Programming Language :: Python :: 3
Classifier: Programming Language :: Python :: 3.3
Classifier: Programming Language :: Python :: 3.4
